visorRobot/__init__.py
visorRobot/visor.py
visorRobot05-0.0.1.dist-info/METADATA
visorRobot05-0.0.1.dist-info/WHEEL
visorRobot05-0.0.1.dist-info/top_level.txt
visorRobot05-0.0.1.dist-info/RECORD
